<?xml version = '1.0' encoding = 'UTF-8'?>
<Relation class="oracle.dbtools.crest.model.design.logical.Relation" name="StdPermAddr_City_FK" directorySegmentName="seg_8" id="C0A3422B-CFE4-1C02-87DD-EB62E29021A2">
<createdBy>leads</createdBy>
<createdTime>2022-05-19 10:23:05 UTC</createdTime>
<ownerDesignName>school_management_datamodel</ownerDesignName>
<engineerTo>
<item key="05B79F77-35A9-E05C-14E8-7FD371603C77" value="true"/>
</engineerTo>
<sourcePk>97CC0AD7-AC84-BD24-2799-8B5FEDAFAA6C</sourcePk>
<identifying>false</identifying>
<optionalSource>true</optionalSource>
<optionalTarget>false</optionalTarget>
<sourceCardinality>1</sourceCardinality>
<sourceEntity>C57E5AD7-02EF-564A-6FC5-62D9E5981965</sourceEntity>
<targetCardinalityString>*</targetCardinalityString>
<targetEntity>1DDBB842-08DA-1AFB-97C7-A737B6C7485A</targetEntity>
<transferable>true</transferable>
<deleteRule>NO ACTION</deleteRule>
</Relation>