<?xml version = '1.0' encoding = 'UTF-8'?>
<Relation class="oracle.dbtools.crest.model.design.logical.Relation" name="ClssTchr_Section_FK" directorySegmentName="seg_8" id="DD406728-2F47-270D-6621-11D9122D331A">
<createdBy>leads</createdBy>
<createdTime>2019-09-02 10:58:26 UTC</createdTime>
<ownerDesignName>school_management_datamodel</ownerDesignName>
<engineerTo>
<item key="05B79F77-35A9-E05C-14E8-7FD371603C77" value="true"/>
</engineerTo>
<sourcePk>4091F68C-6C3E-3B22-EB5A-A547F977DF53</sourcePk>
<identifying>false</identifying>
<optionalSource>true</optionalSource>
<optionalTarget>false</optionalTarget>
<sourceCardinality>1</sourceCardinality>
<sourceEntity>52539A12-8375-94EF-50A1-48000098D687</sourceEntity>
<targetCardinalityString>*</targetCardinalityString>
<targetEntity>1005C6AB-1BB0-513B-67D0-51414AAB4207</targetEntity>
<transferable>true</transferable>
<deleteRule>NO ACTION</deleteRule>
</Relation>