<?xml version = '1.0' encoding = 'UTF-8'?>
<TableProxyOraclev12c class="oracle.dbtools.crest.model.design.storage.oracle.v12c.TableProxyOraclev12c" name="sibling" directorySegmentName="seg_4" id="122D515C-00A0-1B83-00D3-C5B60526F182">
<createdBy>leads</createdBy>
<createdTime>2020-06-02 08:52:46 UTC</createdTime>
<ownerDesignName>school_management_datamodel</ownerDesignName>
<logging>YES</logging>
<partitionedRowMovement>DISABLE</partitionedRowMovement>
<temporaryChanged>false</temporaryChanged>
<accessDriverType>oracle_loader</accessDriverType>
<defaultdir>E0496976-59B7-6E43-AF03-A672DDDC8C73</defaultdir>
<defaultDirName>SMS_DIR</defaultDirName>
<rejectLimit></rejectLimit>
<columnProxies itemClass="oracle.dbtools.crest.model.design.storage.oracle.v12c.ColumnProxyOraclev12c">
<ColumnProxy name="first_name_csv" id="3EF513CE-BC91-CED2-AA16-505E1D5C664F">
<createdBy>leads</createdBy>
<createdTime>2020-06-02 08:52:46 UTC</createdTime>
<ownerDesignName>school_management_datamodel</ownerDesignName>
</ColumnProxy>
<ColumnProxy name="notes" id="4369835C-3D87-1396-5A3F-5A30A368B21A">
<createdBy>leads</createdBy>
<createdTime>2020-06-02 09:06:56 UTC</createdTime>
<ownerDesignName>school_management_datamodel</ownerDesignName>
</ColumnProxy>
<ColumnProxy name="id" id="9B4A5494-C34B-55C7-F148-5DE413EC290E">
<createdBy>leads</createdBy>
<createdTime>2020-06-02 08:52:46 UTC</createdTime>
<ownerDesignName>school_management_datamodel</ownerDesignName>
</ColumnProxy>
</columnProxies>
<indexProxies>
<IndexProxy class="oracle.dbtools.crest.model.design.storage.oracle.v10g.IndexProxyOraclev10g" name="sibling_un_idx" id="7B261E97-04F1-CE2C-12AD-E19362C4D1E2">
<createdBy>leads</createdBy>
<createdTime>2020-06-02 09:07:57 UTC</createdTime>
<ownerDesignName>school_management_datamodel</ownerDesignName>
</IndexProxy>
<IndexProxy class="oracle.dbtools.crest.model.design.storage.oracle.v10g.IndexProxyOraclev10g" name="sibling_pk_idx" id="A9665356-3E9C-6915-9602-826CE6BCCD87">
<createdBy>leads</createdBy>
<createdTime>2020-06-02 09:00:25 UTC</createdTime>
<ownerDesignName>school_management_datamodel</ownerDesignName>
</IndexProxy>
</indexProxies>
<primaryKeys>
<PrimaryKey class="oracle.dbtools.crest.model.design.storage.oracle.v10g.PKProxyOraclev10g" name="sibling_PK" id="0A48CF94-6C21-3D11-3B0F-C3D463C245EB">
<createdBy>leads</createdBy>
<createdTime>2020-06-02 08:52:46 UTC</createdTime>
<ownerDesignName>school_management_datamodel</ownerDesignName>
<indexSort>SORTED</indexSort>
</PrimaryKey>
</primaryKeys>
<uniqueKeys>
<UniqueKey class="oracle.dbtools.crest.model.design.storage.oracle.v10g.UniqueOraclev10g" name="sibling_UN" id="C0EC9F64-1FC7-E5A2-8B34-608FC6F511B3">
<createdBy>leads</createdBy>
<createdTime>2020-06-02 09:06:56 UTC</createdTime>
<ownerDesignName>school_management_datamodel</ownerDesignName>
<indexSort>SORTED</indexSort>
</UniqueKey>
</uniqueKeys>
</TableProxyOraclev12c>