<?xml version = '1.0' encoding = 'UTF-8'?>
<Entity class="oracle.dbtools.crest.model.design.logical.Entity" directorySegmentName="seg_4" id="16AB553D-D4A7-C72B-83B7-E72EC43ABBDC" name="company_document">
<createdBy>leads</createdBy>
<createdTime>2020-05-25 07:12:47 UTC</createdTime>
<comment><![CDATA[Documents of the company]]></comment>
<commentInRDBMS><![CDATA[Documents of the company]]></commentInRDBMS>
<notes><![CDATA[Documents of the company]]></notes>
<ownerDesignName>school_management_datamodel</ownerDesignName>
<engineerTo>
<item key="05B79F77-35A9-E05C-14E8-7FD371603C77" value="true"/>
</engineerTo>
<adequatelyNormalized>NO</adequatelyNormalized>
<expectedVolumes>0</expectedVolumes>
<fwdEngineeringStrategyName>Single Table</fwdEngineeringStrategyName>
<growthPercent>0</growthPercent>
<growthType>Year</growthType>
<maxVolumes>9999999</maxVolumes>
<minVolumes>0</minVolumes>
<normalForm>Third</normalForm>
<preferredAbbreviation>company_document</preferredAbbreviation>
<shortName>company_document</shortName>
<synonym>company_document</synonym>
<synonymToDisplay>company_document</synonymToDisplay>
<createSurrogateKey>true</createSurrogateKey>
<attributes itemClass="oracle.dbtools.crest.model.design.logical.Attribute">
<Attribute name="no#" id="CA95FCF6-C912-BA12-55C5-3CA94F418C4A">
<createdBy>leads</createdBy>
<createdTime>2020-05-25 07:14:45 UTC</createdTime>
<comment><![CDATA[Document number/code]]></comment>
<commentInRDBMS><![CDATA[Document number/code]]></commentInRDBMS>
<notes><![CDATA[Document number/code]]></notes>
<ownerDesignName>school_management_datamodel</ownerDesignName>
<engineerTo>
<item key="05B79F77-35A9-E05C-14E8-7FD371603C77" value="true"/>
</engineerTo>
<use>0</use>
<logicalDatatype>LOGDT024</logicalDatatype>
<domain>324569D7-5905-0BF6-309B-6FFDF4AA5C83</domain>
<ownDataTypeParameters>,,</ownDataTypeParameters>
</Attribute>
<Attribute name="company_code" id="C5A9638B-F7BA-9CD1-07DB-1AEF8FDD2F2E">
<createdBy>leads</createdBy>
<createdTime>2020-05-25 07:13:46 UTC</createdTime>
<comment><![CDATA[Company Code - 10 digits]]></comment>
<commentInRDBMS><![CDATA[Company Code - 10 digits]]></commentInRDBMS>
<generatorID>ED240460-DB93-0CB3-21F9-9EB684BC01AB</generatorID>
<notes><![CDATA[Company Code - 10 digits]]></notes>
<ownerDesignName>school_management_datamodel</ownerDesignName>
<engineerTo>
<item key="05B79F77-35A9-E05C-14E8-7FD371603C77" value="true"/>
</engineerTo>
<referedAttribute>95B99F61-D3E4-28BD-961F-A8F40C4D2CD8</referedAttribute>
<use>0</use>
<logicalDatatype>LOGDT024</logicalDatatype>
<domain>53AB0579-872F-D944-2762-9BC69C2EFEBD</domain>
<ownDataTypeParameters>,,</ownDataTypeParameters>
</Attribute>
<Attribute name="document_code" id="97996F20-BD1E-C272-CB7A-B3292808E57D">
<createdBy>leads</createdBy>
<createdTime>2020-05-25 07:15:42 UTC</createdTime>
<comment><![CDATA[Document Code]]></comment>
<commentInRDBMS><![CDATA[Document Code]]></commentInRDBMS>
<generatorID>E67A4681-2652-65E9-D773-10EC7A59F4FC</generatorID>
<notes><![CDATA[Document Code]]></notes>
<ownerDesignName>school_management_datamodel</ownerDesignName>
<engineerTo>
<item key="05B79F77-35A9-E05C-14E8-7FD371603C77" value="true"/>
</engineerTo>
<referedAttribute>9A92D62E-CB6E-ABD0-AA2F-5635ED3F0875</referedAttribute>
<useDomainConstraints>false</useDomainConstraints>
<use>0</use>
<logicalDatatype>LOGDT024</logicalDatatype>
<domain>CBEC8CB6-CF80-B9B8-6E84-69AFA0E7086B</domain>
<ownDataTypeParameters>,,</ownDataTypeParameters>
</Attribute>
<Attribute name="issuing_authority" id="AAA8C002-B142-DC26-5B63-3346A7C35589">
<createdBy>leads</createdBy>
<createdTime>2020-05-25 07:16:07 UTC</createdTime>
<ownerDesignName>school_management_datamodel</ownerDesignName>
<engineerTo>
<item key="05B79F77-35A9-E05C-14E8-7FD371603C77" value="true"/>
</engineerTo>
<use>0</use>
<logicalDatatype>LOGDT024</logicalDatatype>
<domain>3BB31CEA-DF84-001B-D31D-BF955F6ADDBF</domain>
<ownDataTypeParameters>,,</ownDataTypeParameters>
</Attribute>
<Attribute name="issued_on" id="B535D9A5-1D4B-8D9A-9900-79E9762F57FB">
<createdBy>leads</createdBy>
<createdTime>2020-05-25 07:16:07 UTC</createdTime>
<ownerDesignName>school_management_datamodel</ownerDesignName>
<engineerTo>
<item key="05B79F77-35A9-E05C-14E8-7FD371603C77" value="true"/>
</engineerTo>
<nullsAllowed>true</nullsAllowed>
<use>0</use>
<logicalDatatype>LOGDT007</logicalDatatype>
<domain>57E4E726-0278-DC93-9196-ABB2B37DFF18</domain>
<ownDataTypeParameters>,,</ownDataTypeParameters>
</Attribute>
<Attribute name="valid_upto" id="91B648B8-164A-B79D-B85C-B3A1FD6FFF00">
<createdBy>leads</createdBy>
<createdTime>2020-05-25 07:16:07 UTC</createdTime>
<ownerDesignName>school_management_datamodel</ownerDesignName>
<engineerTo>
<item key="05B79F77-35A9-E05C-14E8-7FD371603C77" value="true"/>
</engineerTo>
<nullsAllowed>true</nullsAllowed>
<use>0</use>
<logicalDatatype>LOGDT007</logicalDatatype>
<domain>57E4E726-0278-DC93-9196-ABB2B37DFF18</domain>
<ownDataTypeParameters>,,</ownDataTypeParameters>
</Attribute>
<Attribute name="uploaded_file" id="C633C48B-7DBB-4D7C-AEFE-65D4E647A5D4">
<createdBy>leads</createdBy>
<createdTime>2020-05-25 07:16:07 UTC</createdTime>
<ownerDesignName>school_management_datamodel</ownerDesignName>
<engineerTo>
<item key="05B79F77-35A9-E05C-14E8-7FD371603C77" value="true"/>
</engineerTo>
<nullsAllowed>true</nullsAllowed>
<use>0</use>
<logicalDatatype>LOGDT029</logicalDatatype>
<domain>AA2BB5A1-AD10-27B7-B0A5-D632AFC3A2BA</domain>
<ownDataTypeParameters>,,</ownDataTypeParameters>
</Attribute>
<Attribute name="mime_type" id="C63CE1B3-B9C9-2101-4700-EAFE4FC29CCA">
<createdBy>leads</createdBy>
<createdTime>2021-06-22 07:49:41 UTC</createdTime>
<comment><![CDATA[pdf/xls/xlsx/jpeg/bmp/doc/docx/png/mp4]]></comment>
<commentInRDBMS><![CDATA[pdf/xls/xlsx/jpeg/bmp/doc/docx/png/mp4]]></commentInRDBMS>
<generatorID>F3AEF40A-3D8C-0D4B-CAEC-4FAFAE603CED</generatorID>
<notes><![CDATA[pdf/xls/xlsx/jpeg/bmp/doc/docx/png/mp4]]></notes>
<ownerDesignName>school_management_datamodel</ownerDesignName>
<engineerTo>
<item key="05B79F77-35A9-E05C-14E8-7FD371603C77" value="true"/>
</engineerTo>
<nullsAllowed>true</nullsAllowed>
<referedAttribute>DD78865C-9278-8EED-0C1D-F37BAF241CA0</referedAttribute>
<use>0</use>
<logicalDatatype>LOGDT024</logicalDatatype>
<domain>C67BAB21-6082-5D9D-27F4-099912620F76</domain>
<ownDataTypeParameters>,,</ownDataTypeParameters>
</Attribute>
<Attribute name="status_name" id="52B4A9C3-78AB-0581-62F8-DF0C9918C46F">
<createdBy>leads</createdBy>
<createdTime>2021-07-19 05:35:08 UTC</createdTime>
<comment><![CDATA[Status Name]]></comment>
<commentInRDBMS><![CDATA[Status Name]]></commentInRDBMS>
<generatorID>2BCF7737-60C2-046A-B46C-41304565BD3F</generatorID>
<notes><![CDATA[Status Name]]></notes>
<ownerDesignName>school_management_datamodel</ownerDesignName>
<engineerTo>
<item key="05B79F77-35A9-E05C-14E8-7FD371603C77" value="true"/>
</engineerTo>
<referedAttribute>8D5DF3E8-8F74-1632-7641-0F9128C78A86</referedAttribute>
<use>0</use>
<logicalDatatype>LOGDT024</logicalDatatype>
<domain>35AF6BA5-100E-363B-D4F8-59F7EA81EED9</domain>
<ownDataTypeParameters>,,</ownDataTypeParameters>
</Attribute>
<Attribute name="descriptions" id="18AEC3D1-A8B2-CE78-9EBE-A1A40E2D0952">
<createdBy>leads</createdBy>
<createdTime>2020-05-25 07:16:07 UTC</createdTime>
<ownerDesignName>school_management_datamodel</ownerDesignName>
<engineerTo>
<item key="05B79F77-35A9-E05C-14E8-7FD371603C77" value="true"/>
</engineerTo>
<nullsAllowed>true</nullsAllowed>
<use>0</use>
<logicalDatatype>LOGDT024</logicalDatatype>
<domain>D8145389-4D0D-CC31-9923-FD4288ACF409</domain>
<ownDataTypeParameters>,,</ownDataTypeParameters>
</Attribute>
<Attribute name="created_by" id="75C2608C-5D74-474F-C332-7EF370C6FE35">
<createdBy>leads</createdBy>
<createdTime>2022-03-30 07:48:44 UTC</createdTime>
<comment><![CDATA[User who created the record]]></comment>
<commentInRDBMS><![CDATA[User who created the record]]></commentInRDBMS>
<notes><![CDATA[User who created the record]]></notes>
<ownerDesignName>school_management_datamodel</ownerDesignName>
<engineerTo>
<item key="05B79F77-35A9-E05C-14E8-7FD371603C77" value="true"/>
</engineerTo>
<nullsAllowed>true</nullsAllowed>
<useDomainConstraints>false</useDomainConstraints>
<use>0</use>
<logicalDatatype>LOGDT024</logicalDatatype>
<domain>FCF40FD2-658F-71B5-EA0B-1055E4223B0E</domain>
<ownDataTypeParameters>,,</ownDataTypeParameters>
<propertyMap>
<property name="engineerTo" value=""/>
</propertyMap>
</Attribute>
<Attribute name="created_on" id="0BE95AFF-A34B-5501-AE37-854E995D665C">
<createdBy>leads</createdBy>
<createdTime>2022-03-30 07:48:44 UTC</createdTime>
<comment><![CDATA[Record created - date and time]]></comment>
<commentInRDBMS><![CDATA[Record created - date and time]]></commentInRDBMS>
<notes><![CDATA[Record created - date and time]]></notes>
<ownerDesignName>school_management_datamodel</ownerDesignName>
<engineerTo>
<item key="05B79F77-35A9-E05C-14E8-7FD371603C77" value="true"/>
</engineerTo>
<nullsAllowed>true</nullsAllowed>
<useDomainConstraints>false</useDomainConstraints>
<use>0</use>
<logicalDatatype>LOGDT015</logicalDatatype>
<domain>4A67150B-1396-BA5B-65B0-74D0D4FA6D8A</domain>
<defaultValue>CURRENT_TIMESTAMP</defaultValue>
<ownDataTypeParameters>,,</ownDataTypeParameters>
<propertyMap>
<property name="engineerTo" value=""/>
</propertyMap>
</Attribute>
<Attribute name="updated_by" id="C920A78D-DBCB-877F-31E4-8522871A9D1F">
<createdBy>leads</createdBy>
<createdTime>2022-03-30 07:48:44 UTC</createdTime>
<comment><![CDATA[User who updated the record]]></comment>
<commentInRDBMS><![CDATA[User who updated the record]]></commentInRDBMS>
<notes><![CDATA[User who updated the record]]></notes>
<ownerDesignName>school_management_datamodel</ownerDesignName>
<engineerTo>
<item key="05B79F77-35A9-E05C-14E8-7FD371603C77" value="true"/>
</engineerTo>
<nullsAllowed>true</nullsAllowed>
<useDomainConstraints>false</useDomainConstraints>
<use>0</use>
<logicalDatatype>LOGDT024</logicalDatatype>
<domain>FCF40FD2-658F-71B5-EA0B-1055E4223B0E</domain>
<ownDataTypeParameters>,,</ownDataTypeParameters>
<propertyMap>
<property name="engineerTo" value=""/>
</propertyMap>
</Attribute>
<Attribute name="changed_on" id="5AB8C1F4-41F1-9A41-16C5-0E3A166E8E2A">
<createdBy>leads</createdBy>
<createdTime>2022-03-30 07:48:44 UTC</createdTime>
<comment><![CDATA[Last record changed - date and time]]></comment>
<commentInRDBMS><![CDATA[Last record changed - date and time]]></commentInRDBMS>
<notes><![CDATA[Last record changed - date and time]]></notes>
<ownerDesignName>school_management_datamodel</ownerDesignName>
<engineerTo>
<item key="05B79F77-35A9-E05C-14E8-7FD371603C77" value="true"/>
</engineerTo>
<nullsAllowed>true</nullsAllowed>
<useDomainConstraints>false</useDomainConstraints>
<use>0</use>
<logicalDatatype>LOGDT015</logicalDatatype>
<domain>4A67150B-1396-BA5B-65B0-74D0D4FA6D8A</domain>
<defaultValue>CURRENT_TIMESTAMP</defaultValue>
<ownDataTypeParameters>,,</ownDataTypeParameters>
<propertyMap>
<property name="engineerTo" value=""/>
</propertyMap>
</Attribute>
</attributes>
<identifiers itemClass="oracle.dbtools.crest.model.design.logical.CandidateKey">
<identifier id="715F4709-2FB0-5B85-E61B-C6F570406730" name="company_document_UN">
<createdBy>leads</createdBy>
<createdTime>2020-05-25 07:17:55 UTC</createdTime>
<ownerDesignName>school_management_datamodel</ownerDesignName>
<engineerTo>
<item key="05B79F77-35A9-E05C-14E8-7FD371603C77" value="true"/>
</engineerTo>
<newElementsIDs>CA95FCF6-C912-BA12-55C5-3CA94F418C4A,ED240460-DB93-0CB3-21F9-9EB684BC01AB,E67A4681-2652-65E9-D773-10EC7A59F4FC</newElementsIDs>
<usedAttributes>
<attributeRef>CA95FCF6-C912-BA12-55C5-3CA94F418C4A</attributeRef>
<attributeRef>C5A9638B-F7BA-9CD1-07DB-1AEF8FDD2F2E</attributeRef>
<attributeRef>97996F20-BD1E-C272-CB7A-B3292808E57D</attributeRef>
</usedAttributes>
</identifier>
</identifiers>
</Entity>