<?xml version = '1.0' encoding = 'UTF-8'?>
<TableProxyOraclev12c class="oracle.dbtools.crest.model.design.storage.oracle.v12c.TableProxyOraclev12c" name="leave" directorySegmentName="seg_5" id="705163D4-8540-1211-8EB3-AC13EB6E554F">
<createdBy>leads</createdBy>
<createdTime>2019-08-06 05:59:05 UTC</createdTime>
<ownerDesignName>school_management_datamodel</ownerDesignName>
<logging>YES</logging>
<partitionedRowMovement>DISABLE</partitionedRowMovement>
<temporaryChanged>false</temporaryChanged>
<accessDriverType>oracle_loader</accessDriverType>
<defaultdir>E0496976-59B7-6E43-AF03-A672DDDC8C73</defaultdir>
<defaultDirName>SMS_DIR</defaultDirName>
<rejectLimit></rejectLimit>
<columnProxies itemClass="oracle.dbtools.crest.model.design.storage.oracle.v12c.ColumnProxyOraclev12c">
<ColumnProxy name="descriptions" id="278ECD85-65F9-9246-D070-BB03098131F2">
<createdBy>leads</createdBy>
<createdTime>2019-08-06 05:59:05 UTC</createdTime>
<ownerDesignName>school_management_datamodel</ownerDesignName>
</ColumnProxy>
<ColumnProxy name="name" id="38D6946C-E952-7F32-1493-A4585E212964">
<createdBy>leads</createdBy>
<createdTime>2019-08-06 05:59:05 UTC</createdTime>
<ownerDesignName>school_management_datamodel</ownerDesignName>
</ColumnProxy>
<ColumnProxy name="code" id="8CD4EF4D-BC9B-C74B-B1B6-681200F014C0">
<createdBy>leads</createdBy>
<createdTime>2019-08-06 05:59:05 UTC</createdTime>
<ownerDesignName>school_management_datamodel</ownerDesignName>
</ColumnProxy>
<ColumnProxy name="pseudo" id="FDF3D320-E6F5-87AE-8678-62CB59E027F7">
<createdBy>leads</createdBy>
<createdTime>2020-05-26 05:36:27 UTC</createdTime>
<ownerDesignName>school_management_datamodel</ownerDesignName>
</ColumnProxy>
</columnProxies>
<indexProxies>
<IndexProxy class="oracle.dbtools.crest.model.design.storage.oracle.v10g.IndexProxyOraclev10g" name="leave_un_idx" id="1983B37A-061C-85DE-4DCD-C11E81A9EC32">
<createdBy>leads</createdBy>
<createdTime>2019-08-06 05:59:56 UTC</createdTime>
<ownerDesignName>school_management_datamodel</ownerDesignName>
</IndexProxy>
<IndexProxy class="oracle.dbtools.crest.model.design.storage.oracle.v10g.IndexProxyOraclev10g" name="leave_pk_idx" id="776B4FE9-F79A-45DB-9A4D-9727077870AB">
<createdBy>leads</createdBy>
<createdTime>2019-08-06 05:59:56 UTC</createdTime>
<ownerDesignName>school_management_datamodel</ownerDesignName>
</IndexProxy>
<IndexProxy class="oracle.dbtools.crest.model.design.storage.oracle.v10g.IndexProxyOraclev10g" name="leave_un2_idx" id="B3373746-807C-451B-828A-628FDCB23E00">
<createdBy>leads</createdBy>
<createdTime>2021-03-23 11:48:35 UTC</createdTime>
<ownerDesignName>school_management_datamodel</ownerDesignName>
</IndexProxy>
</indexProxies>
<primaryKeys>
<PrimaryKey class="oracle.dbtools.crest.model.design.storage.oracle.v10g.PKProxyOraclev10g" name="leave_PK" id="94FA564D-E59C-9349-2744-A7A61993ABB9">
<createdBy>leads</createdBy>
<createdTime>2019-08-06 05:59:05 UTC</createdTime>
<ownerDesignName>school_management_datamodel</ownerDesignName>
<indexSort>SORTED</indexSort>
</PrimaryKey>
</primaryKeys>
<uniqueKeys>
<UniqueKey class="oracle.dbtools.crest.model.design.storage.oracle.v10g.UniqueOraclev10g" name="leave_UN" id="5D3530A2-BEFC-DB17-E6CA-8ADCD813A93B">
<createdBy>leads</createdBy>
<createdTime>2019-08-06 05:59:05 UTC</createdTime>
<ownerDesignName>school_management_datamodel</ownerDesignName>
<indexSort>SORTED</indexSort>
</UniqueKey>
<UniqueKey class="oracle.dbtools.crest.model.design.storage.oracle.v10g.UniqueOraclev10g" name="leave_UN2" id="DBD204B9-03B6-8EA2-707A-70B8090F001E">
<createdBy>leads</createdBy>
<createdTime>2021-03-23 11:46:50 UTC</createdTime>
<ownerDesignName>school_management_datamodel</ownerDesignName>
<indexSort>SORTED</indexSort>
</UniqueKey>
</uniqueKeys>
</TableProxyOraclev12c>
