<?xml version = '1.0' encoding = 'UTF-8'?>
<Relation class="oracle.dbtools.crest.model.design.logical.Relation" name="AssessOrd_Ordinal_FK" directorySegmentName="seg_0" id="BCF7A2DE-3A98-B31D-C2D3-3B90413570A5">
<createdBy>leads</createdBy>
<createdTime>2020-03-14 07:54:49 UTC</createdTime>
<ownerDesignName>school_management_datamodel</ownerDesignName>
<engineerTo>
<item key="05B79F77-35A9-E05C-14E8-7FD371603C77" value="true"/>
</engineerTo>
<sourcePk>846446EA-21C0-EA75-8733-18A34929E88A</sourcePk>
<identifying>true</identifying>
<optionalSource>true</optionalSource>
<optionalTarget>false</optionalTarget>
<sourceCardinality>1</sourceCardinality>
<sourceEntity>0746D729-00EB-A531-0D83-34683F33639E</sourceEntity>
<targetCardinalityString>*</targetCardinalityString>
<targetEntity>B6B76261-9A8F-902A-723D-E8D12BBCF018</targetEntity>
<transferable>true</transferable>
<deleteRule>NO ACTION</deleteRule>
</Relation>