<?xml version = '1.0' encoding = 'UTF-8'?>
<Relation class="oracle.dbtools.crest.model.design.logical.Relation" name="SyllabOrd_Ordinal_FK" directorySegmentName="seg_15" id="432AC118-26CD-738B-B666-94045E84B9F8">
<createdBy>leads</createdBy>
<createdTime>2020-12-05 06:10:15 UTC</createdTime>
<ownerDesignName>school_management_datamodel</ownerDesignName>
<engineerTo>
<item key="05B79F77-35A9-E05C-14E8-7FD371603C77" value="true"/>
</engineerTo>
<sourcePk>846446EA-21C0-EA75-8733-18A34929E88A</sourcePk>
<identifying>true</identifying>
<optionalSource>true</optionalSource>
<optionalTarget>false</optionalTarget>
<sourceCardinality>1</sourceCardinality>
<sourceEntity>0746D729-00EB-A531-0D83-34683F33639E</sourceEntity>
<targetCardinalityString>*</targetCardinalityString>
<targetEntity>80D7F71F-95AB-0BAF-8B48-5BF133DC1A9D</targetEntity>
<transferable>true</transferable>
<deleteRule>NO ACTION</deleteRule>
</Relation>