<?xml version = '1.0' encoding = 'UTF-8'?>
<TableProxyOraclev12c class="oracle.dbtools.crest.model.design.storage.oracle.v12c.TableProxyOraclev12c" name="emp_leave" directorySegmentName="seg_6" id="4EDFC80E-7A0C-19C9-A381-A3EF56C7A8E1">
<createdBy>leads</createdBy>
<createdTime>2022-09-20 08:59:36 UTC</createdTime>
<ownerDesignName>school_management_datamodel</ownerDesignName>
<logging>YES</logging>
<partitionedRowMovement>DISABLE</partitionedRowMovement>
<temporaryChanged>false</temporaryChanged>
<accessDriverType>oracle_loader</accessDriverType>
<rejectLimit></rejectLimit>
<columnProxies itemClass="oracle.dbtools.crest.model.design.storage.oracle.v12c.ColumnProxyOraclev12c">
<ColumnProxy name="delegation_id" id="2A52C451-ADE3-277E-41B6-8E53289B06D7">
<createdBy>leads</createdBy>
<createdTime>2022-09-20 08:59:36 UTC</createdTime>
<ownerDesignName>school_management_datamodel</ownerDesignName>
</ColumnProxy>
<ColumnProxy name="id" id="375EADD5-6A58-BC39-208A-970C6330E580">
<createdBy>leads</createdBy>
<createdTime>2022-09-20 08:59:36 UTC</createdTime>
<ownerDesignName>school_management_datamodel</ownerDesignName>
</ColumnProxy>
<ColumnProxy name="created_on" id="40698015-2CC1-5129-2FC0-87750DDECC78">
<createdBy>leads</createdBy>
<createdTime>2022-09-20 08:59:36 UTC</createdTime>
<ownerDesignName>school_management_datamodel</ownerDesignName>
<defaultValue>CURRENT_TIMESTAMP</defaultValue>
</ColumnProxy>
<ColumnProxy name="reasons" id="416AA998-40D4-E905-E038-214B218C6542">
<createdBy>leads</createdBy>
<createdTime>2022-09-20 08:59:36 UTC</createdTime>
<ownerDesignName>school_management_datamodel</ownerDesignName>
</ColumnProxy>
<ColumnProxy name="updated_by" id="47CD5E75-A556-95D9-0742-CD2B37D1EDBC">
<createdBy>leads</createdBy>
<createdTime>2022-09-20 08:59:36 UTC</createdTime>
<ownerDesignName>school_management_datamodel</ownerDesignName>
</ColumnProxy>
<ColumnProxy name="leave_status" id="4AD73EEE-2DF6-FA3D-7CF5-D203F31DF16E">
<createdBy>leads</createdBy>
<createdTime>2022-09-21 03:26:34 UTC</createdTime>
<ownerDesignName>school_management_datamodel</ownerDesignName>
</ColumnProxy>
<ColumnProxy name="effective_upto" id="4B608897-EA49-9DCE-B6A2-25DFF796A290">
<createdBy>leads</createdBy>
<createdTime>2022-09-20 08:59:36 UTC</createdTime>
<ownerDesignName>school_management_datamodel</ownerDesignName>
</ColumnProxy>
<ColumnProxy name="company_code" id="69863A9B-86D8-170B-A317-E313FC59C72F">
<createdBy>leads</createdBy>
<createdTime>2022-09-20 08:59:36 UTC</createdTime>
<ownerDesignName>school_management_datamodel</ownerDesignName>
</ColumnProxy>
<ColumnProxy name="incident_status" id="6C9B52BF-EA11-44E3-8B71-B8C3351B7E86">
<createdBy>leads</createdBy>
<createdTime>2022-09-21 03:26:34 UTC</createdTime>
<ownerDesignName>school_management_datamodel</ownerDesignName>
</ColumnProxy>
<ColumnProxy name="changed_on" id="7B62C827-CDF9-9F8F-8292-0A601FA19846">
<createdBy>leads</createdBy>
<createdTime>2022-09-20 08:59:36 UTC</createdTime>
<ownerDesignName>school_management_datamodel</ownerDesignName>
<defaultValue>CURRENT_TIMESTAMP</defaultValue>
</ColumnProxy>
<ColumnProxy name="closed_on" id="8493FBB8-D027-23D4-7B5C-DFACE889D0CB">
<createdBy>leads</createdBy>
<createdTime>2022-09-20 08:59:36 UTC</createdTime>
<ownerDesignName>school_management_datamodel</ownerDesignName>
</ColumnProxy>
<ColumnProxy name="employee_id" id="87D631AF-9585-2EDF-9B81-79EFBBC6DC41">
<createdBy>leads</createdBy>
<createdTime>2022-09-20 08:59:36 UTC</createdTime>
<ownerDesignName>school_management_datamodel</ownerDesignName>
</ColumnProxy>
<ColumnProxy name="doa_comments" id="8FD140D8-8379-D338-95A6-EC8805063DAC">
<createdBy>leads</createdBy>
<createdTime>2022-09-20 08:59:36 UTC</createdTime>
<ownerDesignName>school_management_datamodel</ownerDesignName>
</ColumnProxy>
<ColumnProxy name="batch_no#" id="91304D34-59F0-66A8-5457-37639E148049">
<createdBy>leads</createdBy>
<createdTime>2022-09-20 08:59:36 UTC</createdTime>
<ownerDesignName>school_management_datamodel</ownerDesignName>
</ColumnProxy>
<ColumnProxy name="effective_from" id="B91A71D5-E84D-AFEA-2D14-7A360C5851EA">
<createdBy>leads</createdBy>
<createdTime>2022-09-20 08:59:36 UTC</createdTime>
<ownerDesignName>school_management_datamodel</ownerDesignName>
</ColumnProxy>
<ColumnProxy name="closed_by" id="C7DBD15E-A13D-A4C0-762C-813B401866C1">
<createdBy>leads</createdBy>
<createdTime>2022-09-20 08:59:36 UTC</createdTime>
<ownerDesignName>school_management_datamodel</ownerDesignName>
</ColumnProxy>
<ColumnProxy name="created_by" id="D5FD823A-4E45-DBA6-02CB-B6F5F2483C3B">
<createdBy>leads</createdBy>
<createdTime>2022-09-20 08:59:36 UTC</createdTime>
<ownerDesignName>school_management_datamodel</ownerDesignName>
</ColumnProxy>
<ColumnProxy name="leave_code" id="DC2C462A-272C-945D-F5F4-00DE3B8C1023">
<createdBy>leads</createdBy>
<createdTime>2022-09-20 08:59:36 UTC</createdTime>
<ownerDesignName>school_management_datamodel</ownerDesignName>
</ColumnProxy>
</columnProxies>
<indexProxies>
<IndexProxy class="oracle.dbtools.crest.model.design.storage.oracle.v10g.IndexProxyOraclev10g" name="emp_leave_lvc_idx" id="4B08E60D-9122-0FFB-8B79-56BBD6A04F03">
<createdBy>leads</createdBy>
<createdTime>2022-09-20 09:03:03 UTC</createdTime>
<ownerDesignName>school_management_datamodel</ownerDesignName>
</IndexProxy>
<IndexProxy class="oracle.dbtools.crest.model.design.storage.oracle.v10g.IndexProxyOraclev10g" name="emp_leave_cmp_idx" id="573E25F1-738D-222D-12E5-A5984A943CD7">
<createdBy>leads</createdBy>
<createdTime>2022-09-20 09:03:03 UTC</createdTime>
<ownerDesignName>school_management_datamodel</ownerDesignName>
</IndexProxy>
<IndexProxy class="oracle.dbtools.crest.model.design.storage.oracle.v10g.IndexProxyOraclev10g" name="emp_leave_un_idx" id="72BC5223-ED25-DBA7-92E3-3B1C0AD33604">
<createdBy>leads</createdBy>
<createdTime>2022-09-20 09:05:36 UTC</createdTime>
<ownerDesignName>school_management_datamodel</ownerDesignName>
</IndexProxy>
<IndexProxy class="oracle.dbtools.crest.model.design.storage.oracle.v10g.IndexProxyOraclev10g" name="emp_leave_pk_idx" id="A0787C92-6F34-1428-6C6D-D0918BCD33F0">
<createdBy>leads</createdBy>
<createdTime>2022-09-20 09:05:36 UTC</createdTime>
<ownerDesignName>school_management_datamodel</ownerDesignName>
</IndexProxy>
<IndexProxy class="oracle.dbtools.crest.model.design.storage.oracle.v10g.IndexProxyOraclev10g" name="emp_leave_dlgn_idx" id="AA3D0558-4FE7-3272-6E3E-8DFD799BBC07">
<createdBy>leads</createdBy>
<createdTime>2022-09-20 09:03:03 UTC</createdTime>
<ownerDesignName>school_management_datamodel</ownerDesignName>
</IndexProxy>
<IndexProxy class="oracle.dbtools.crest.model.design.storage.oracle.v10g.IndexProxyOraclev10g" name="emp_leave_stts_idx" id="BB84D007-BFC4-3B68-4F0F-86EA574DF4F7">
<createdBy>leads</createdBy>
<createdTime>2022-09-20 09:03:03 UTC</createdTime>
<ownerDesignName>school_management_datamodel</ownerDesignName>
</IndexProxy>
<IndexProxy class="oracle.dbtools.crest.model.design.storage.oracle.v10g.IndexProxyOraclev10g" name="emp_leave_emp_idx" id="D4939C76-D418-58FE-01F1-C181C3851BC0">
<createdBy>leads</createdBy>
<createdTime>2022-09-20 09:03:03 UTC</createdTime>
<ownerDesignName>school_management_datamodel</ownerDesignName>
</IndexProxy>
<IndexProxy class="oracle.dbtools.crest.model.design.storage.oracle.v10g.IndexProxyOraclev10g" name="emp_leave_btch_idx" id="FAFD66F4-DCCA-B04B-F374-2F50F301E361">
<createdBy>leads</createdBy>
<createdTime>2022-09-20 09:03:03 UTC</createdTime>
<ownerDesignName>school_management_datamodel</ownerDesignName>
</IndexProxy>
<IndexProxy class="oracle.dbtools.crest.model.design.storage.oracle.v10g.IndexProxyOraclev10g" name="emp_leave_incd_idx" id="FB04384D-0269-6D2D-F87A-E83C401AAF24">
<createdBy>leads</createdBy>
<createdTime>2022-09-20 09:03:03 UTC</createdTime>
<ownerDesignName>school_management_datamodel</ownerDesignName>
</IndexProxy>
</indexProxies>
<foreignKeys>
<ForeignKey class="oracle.dbtools.crest.model.design.storage.oracle.v10g.FKProxyOraclev10g" name="EmpLv_Company_FK" id="588A2814-90F9-4624-E37B-01EF6120C4B6">
<createdBy>leads</createdBy>
<createdTime>2022-09-20 08:59:36 UTC</createdTime>
<ownerDesignName>school_management_datamodel</ownerDesignName>
</ForeignKey>
<ForeignKey class="oracle.dbtools.crest.model.design.storage.oracle.v10g.FKProxyOraclev10g" name="EmpLv_LeaveStatus_FK" id="5A7192DD-217D-9BB9-D879-D6A90313B437">
<createdBy>leads</createdBy>
<createdTime>2022-09-21 03:26:34 UTC</createdTime>
<ownerDesignName>school_management_datamodel</ownerDesignName>
</ForeignKey>
<ForeignKey class="oracle.dbtools.crest.model.design.storage.oracle.v10g.FKProxyOraclev10g" name="EmpLv_Incident_FK" id="68C26DF4-AB96-9A7A-DA02-4D3514B236E0">
<createdBy>leads</createdBy>
<createdTime>2022-09-21 03:26:34 UTC</createdTime>
<ownerDesignName>school_management_datamodel</ownerDesignName>
</ForeignKey>
<ForeignKey class="oracle.dbtools.crest.model.design.storage.oracle.v10g.FKProxyOraclev10g" name="EmpLv_Leave_FK" id="6B3922FE-64C8-9E4C-B182-5E06307C0A9D">
<createdBy>leads</createdBy>
<createdTime>2022-09-20 08:59:36 UTC</createdTime>
<ownerDesignName>school_management_datamodel</ownerDesignName>
</ForeignKey>
<ForeignKey class="oracle.dbtools.crest.model.design.storage.oracle.v10g.FKProxyOraclev10g" name="EmpLv_Employee_FK" id="7CBD38E2-46E3-6B08-D96B-E9910171732B">
<createdBy>leads</createdBy>
<createdTime>2022-09-20 08:59:36 UTC</createdTime>
<ownerDesignName>school_management_datamodel</ownerDesignName>
</ForeignKey>
<ForeignKey class="oracle.dbtools.crest.model.design.storage.oracle.v10g.FKProxyOraclev10g" name="EmpLv_Delegation_FK" id="822B13DE-FEEC-B681-D731-4CA2761DA52C">
<createdBy>leads</createdBy>
<createdTime>2022-09-20 08:59:36 UTC</createdTime>
<ownerDesignName>school_management_datamodel</ownerDesignName>
</ForeignKey>
<ForeignKey class="oracle.dbtools.crest.model.design.storage.oracle.v10g.FKProxyOraclev10g" name="EmpLv_Batch_FK" id="92F6E4F3-3806-1732-8795-D918EA067D75">
<createdBy>leads</createdBy>
<createdTime>2022-09-20 08:59:36 UTC</createdTime>
<ownerDesignName>school_management_datamodel</ownerDesignName>
</ForeignKey>
</foreignKeys>
<primaryKeys>
<PrimaryKey class="oracle.dbtools.crest.model.design.storage.oracle.v10g.PKProxyOraclev10g" name="emp_leave_pk" id="FCE5369A-48E0-4F74-6EFC-96BE0D09689E">
<createdBy>leads</createdBy>
<createdTime>2022-09-20 08:59:36 UTC</createdTime>
<ownerDesignName>school_management_datamodel</ownerDesignName>
<indexSort>SORTED</indexSort>
</PrimaryKey>
</primaryKeys>
<uniqueKeys>
<UniqueKey class="oracle.dbtools.crest.model.design.storage.oracle.v10g.UniqueOraclev10g" name="emp_leave_un" id="ECEA62BB-E274-D38D-6413-F6003B0248EC">
<createdBy>leads</createdBy>
<createdTime>2022-09-20 08:59:36 UTC</createdTime>
<ownerDesignName>school_management_datamodel</ownerDesignName>
<indexSort>SORTED</indexSort>
</UniqueKey>
</uniqueKeys>
</TableProxyOraclev12c>