<?xml version = '1.0' encoding = 'UTF-8'?>
<TableProxyOraclev12c class="oracle.dbtools.crest.model.design.storage.oracle.v12c.TableProxyOraclev12c" name="clockwork" directorySegmentName="seg_6" id="7E360FF8-DF16-8C10-55A1-319EAAA27C6F">
<createdBy>leads</createdBy>
<createdTime>2020-05-21 10:07:15 UTC</createdTime>
<ownerDesignName>school_management_datamodel</ownerDesignName>
<logging>YES</logging>
<partitionedRowMovement>DISABLE</partitionedRowMovement>
<temporaryChanged>false</temporaryChanged>
<accessDriverType>oracle_loader</accessDriverType>
<defaultdir>E0496976-59B7-6E43-AF03-A672DDDC8C73</defaultdir>
<defaultDirName>SMS_DIR</defaultDirName>
<rejectLimit></rejectLimit>
<columnProxies itemClass="oracle.dbtools.crest.model.design.storage.oracle.v12c.ColumnProxyOraclev12c">
<ColumnProxy name="pseudo_name" id="063CBEC1-3B6A-E9AC-395E-A0410632AB2D">
<createdBy>leads</createdBy>
<createdTime>2020-05-21 10:07:15 UTC</createdTime>
<ownerDesignName>school_management_datamodel</ownerDesignName>
</ColumnProxy>
<ColumnProxy name="days" id="09BCBCB1-D073-AC94-D063-85D0ECFF4B10">
<createdBy>leads</createdBy>
<createdTime>2020-05-21 10:07:15 UTC</createdTime>
<ownerDesignName>school_management_datamodel</ownerDesignName>
</ColumnProxy>
<ColumnProxy name="descriptions" id="2D6BD264-FEF2-D78F-7A14-3EA7F7D60733">
<createdBy>leads</createdBy>
<createdTime>2020-05-21 10:07:15 UTC</createdTime>
<ownerDesignName>school_management_datamodel</ownerDesignName>
</ColumnProxy>
<ColumnProxy name="name" id="73604239-A230-D8D2-E013-7B35E8A8DE2F">
<createdBy>leads</createdBy>
<createdTime>2020-05-21 10:07:15 UTC</createdTime>
<ownerDesignName>school_management_datamodel</ownerDesignName>
</ColumnProxy>
<ColumnProxy name="code" id="84875335-C068-CB51-EB15-3B0060396811">
<createdBy>leads</createdBy>
<createdTime>2020-05-21 10:07:15 UTC</createdTime>
<ownerDesignName>school_management_datamodel</ownerDesignName>
</ColumnProxy>
</columnProxies>
<indexProxies>
<IndexProxy class="oracle.dbtools.crest.model.design.storage.oracle.v10g.IndexProxyOraclev10g" name="clockwork_un_idx" id="3E8BC45C-6F83-43FC-86EB-A6D4D7DC49D2">
<createdBy>leads</createdBy>
<createdTime>2021-06-08 09:57:24 UTC</createdTime>
<ownerDesignName>school_management_datamodel</ownerDesignName>
</IndexProxy>
<IndexProxy class="oracle.dbtools.crest.model.design.storage.oracle.v10g.IndexProxyOraclev10g" name="clockwork_un2_idx" id="C369297F-56DF-2201-A316-66B7078D0287">
<createdBy>leads</createdBy>
<createdTime>2021-06-08 09:57:24 UTC</createdTime>
<ownerDesignName>school_management_datamodel</ownerDesignName>
</IndexProxy>
<IndexProxy class="oracle.dbtools.crest.model.design.storage.oracle.v10g.IndexProxyOraclev10g" name="clockwork_un3_idx" id="C910B9E3-A914-8111-4637-880DD0F27FB0">
<createdBy>leads</createdBy>
<createdTime>2021-06-08 09:57:24 UTC</createdTime>
<ownerDesignName>school_management_datamodel</ownerDesignName>
</IndexProxy>
<IndexProxy class="oracle.dbtools.crest.model.design.storage.oracle.v10g.IndexProxyOraclev10g" name="clockwork_pk_idx" id="EEFE6483-0C6F-4D98-4810-04332B75CF33">
<createdBy>leads</createdBy>
<createdTime>2021-06-08 09:57:24 UTC</createdTime>
<ownerDesignName>school_management_datamodel</ownerDesignName>
</IndexProxy>
</indexProxies>
<primaryKeys>
<PrimaryKey class="oracle.dbtools.crest.model.design.storage.oracle.v10g.PKProxyOraclev10g" name="clockwork_PK" id="6EBB934D-35EF-1A2E-7CBF-2E467A71B4E2">
<createdBy>leads</createdBy>
<createdTime>2020-05-21 10:07:15 UTC</createdTime>
<ownerDesignName>school_management_datamodel</ownerDesignName>
<indexSort>SORTED</indexSort>
</PrimaryKey>
</primaryKeys>
<uniqueKeys>
<UniqueKey class="oracle.dbtools.crest.model.design.storage.oracle.v10g.UniqueOraclev10g" name="clockwork_UN3" id="408FEBE6-6E40-23A5-5BCE-B6BFA4144846">
<createdBy>leads</createdBy>
<createdTime>2021-06-08 09:53:02 UTC</createdTime>
<ownerDesignName>school_management_datamodel</ownerDesignName>
<indexSort>SORTED</indexSort>
</UniqueKey>
<UniqueKey class="oracle.dbtools.crest.model.design.storage.oracle.v10g.UniqueOraclev10g" name="clockwise_UN" id="C6FFC112-DB28-8C39-4F30-0F6115D67120">
<createdBy>leads</createdBy>
<createdTime>2020-05-21 10:07:15 UTC</createdTime>
<ownerDesignName>school_management_datamodel</ownerDesignName>
<indexSort>SORTED</indexSort>
</UniqueKey>
<UniqueKey class="oracle.dbtools.crest.model.design.storage.oracle.v10g.UniqueOraclev10g" name="clockwork_UN2" id="F0C863E8-2ADB-61E4-10E4-DAA6D0AE7CCF">
<createdBy>leads</createdBy>
<createdTime>2021-06-08 09:53:02 UTC</createdTime>
<ownerDesignName>school_management_datamodel</ownerDesignName>
<indexSort>SORTED</indexSort>
</UniqueKey>
</uniqueKeys>
</TableProxyOraclev12c>